{
  "steps": {
    "2025-11-23": {
      "steps": 0,
      "distance": 0,
      "calories": 0
    },
    "2025-11-24": {
      "steps": 0,
      "distance": 0,
      "calories": 0
    },
    "2025-11-25": {
      "steps": 0,
      "distance": 0,
      "calories": 0
    },
    "2025-11-26": {
      "steps": 0,
      "distance": 0,
      "calories": 0
    },
    "2025-11-27": {
      "steps": 0,
      "distance": 0,
      "calories": 0
    },
    "2025-11-28": {
      "steps": 0,
      "distance": 0,
      "calories": 0
    },
    "2025-11-29": {
      "steps": 0,
      "distance": 0,
      "calories": 0
    },
    "2025-11-30": {
      "steps": 0,
      "distance": 0,
      "calories": 0
    },
    "2025-12-01": {
      "steps": 0,
      "distance": 0,
      "calories": 0
    },
    "2025-12-02": {
      "steps": 0,
      "distance": 0,
      "calories": 0
    },
    "2025-12-03": {
      "steps": 0,
      "distance": 0,
      "calories": 0
    },
    "2025-12-04": {
      "steps": 0,
      "distance": 0,
      "calories": 0
    },
    "2025-12-05": {
      "steps": 0,
      "distance": 0,
      "calories": 0
    },
    "2025-12-06": {
      "steps": 0,
      "distance": 0,
      "calories": 0
    },
    "2025-12-07": {
      "steps": 0,
      "distance": 0,
      "calories": 0
    },
    "2025-12-08": {
      "steps": 0,
      "distance": 0,
      "calories": 0
    },
    "2025-12-09": {
      "steps": 0,
      "distance": 0,
      "calories": 0
    },
    "2025-12-10": {
      "steps": 0,
      "distance": 0,
      "calories": 0
    },
    "2025-12-11": {
      "steps": 0,
      "distance": 0,
      "calories": 0
    },
    "2025-12-12": {
      "steps": 0,
      "distance": 0,
      "calories": 0
    },
    "2025-12-13": {
      "steps": 0,
      "distance": 0,
      "calories": 0
    },
    "2025-12-14": {
      "steps": 0,
      "distance": 0,
      "calories": 0
    },
    "2025-12-15": {
      "steps": 0,
      "distance": 0,
      "calories": 0
    },
    "2025-12-16": {
      "steps": 0,
      "distance": 0,
      "calories": 0
    },
    "2025-12-17": {
      "steps": 0,
      "distance": 0,
      "calories": 0
    },
    "2025-12-18": {
      "steps": 0,
      "distance": 0,
      "calories": 0
    },
    "2025-12-19": {
      "steps": 0,
      "distance": 0,
      "calories": 0
    },
    "2025-12-20": {
      "steps": 0,
      "distance": 0,
      "calories": 0
    },
    "2025-12-21": {
      "steps": 0,
      "distance": 0,
      "calories": 0
    },
    "2025-12-22": {
      "steps": 0,
      "distance": 0,
      "calories": 0
    },
    "2025-12-23": {
      "steps": 0,
      "distance": 0,
      "calories": 0
    },
    "2025-12-24": {
      "steps": 0,
      "distance": 0,
      "calories": 0
    },
    "2025-12-25": {
      "steps": 0,
      "distance": 0,
      "calories": 0
    },
    "2025-12-26": {
      "steps": 0,
      "distance": 0,
      "calories": 0
    },
    "2025-12-27": {
      "steps": 0,
      "distance": 0,
      "calories": 0
    },
    "2025-12-28": {
      "steps": 0,
      "distance": 0,
      "calories": 0
    },
    "2025-12-29": {
      "steps": 0,
      "distance": 0,
      "calories": 0
    },
    "2025-12-30": {
      "steps": 0,
      "distance": 0,
      "calories": 0
    },
    "2025-12-31": {
      "steps": 0,
      "distance": 0,
      "calories": 0
    },
    "2026-01-01": {
      "steps": 0,
      "distance": 0,
      "calories": 0
    },
    "2026-01-02": {
      "steps": 0,
      "distance": 0,
      "calories": 0
    },
    "2026-01-03": {
      "steps": 0,
      "distance": 0,
      "calories": 0
    },
    "2026-01-04": {
      "steps": 0,
      "distance": 0,
      "calories": 0
    },
    "2026-01-05": {
      "steps": 0,
      "distance": 0,
      "calories": 0
    },
    "2026-01-06": {
      "steps": 0,
      "distance": 0,
      "calories": 0
    },
    "2026-01-07": {
      "steps": 0,
      "distance": 0,
      "calories": 0
    },
    "2026-01-08": {
      "steps": 0,
      "distance": 0,
      "calories": 0
    },
    "2026-01-09": {
      "steps": 0,
      "distance": 0,
      "calories": 0
    },
    "2026-01-10": {
      "steps": 0,
      "distance": 0,
      "calories": 0
    },
    "2026-01-11": {
      "steps": 0,
      "distance": 0,
      "calories": 0
    },
    "2026-01-12": {
      "steps": 0,
      "distance": 0,
      "calories": 0
    },
    "2026-01-13": {
      "steps": 0,
      "distance": 0,
      "calories": 0
    },
    "2026-01-14": {
      "steps": 0,
      "distance": 0,
      "calories": 0
    },
    "2026-01-15": {
      "steps": 0,
      "distance": 0,
      "calories": 0
    },
    "2026-01-16": {
      "steps": 0,
      "distance": 0,
      "calories": 0
    },
    "2026-01-17": {
      "steps": 0,
      "distance": 0,
      "calories": 0
    },
    "2026-01-18": {
      "steps": 0,
      "distance": 0,
      "calories": 0
    },
    "2026-01-19": {
      "steps": 0,
      "distance": 0,
      "calories": 0
    },
    "2026-01-20": {
      "steps": 0,
      "distance": 0,
      "calories": 0
    },
    "2026-01-21": {
      "steps": 0,
      "distance": 0,
      "calories": 0
    },
    "2026-01-22": {
      "steps": 0,
      "distance": 0,
      "calories": 0
    },
    "2026-01-23": {
      "steps": 0,
      "distance": 0,
      "calories": 0
    },
    "2026-01-24": {
      "steps": 0,
      "distance": 0,
      "calories": 0
    },
    "2026-01-25": {
      "steps": 0,
      "distance": 0,
      "calories": 0
    },
    "2026-01-26": {
      "steps": 0,
      "distance": 0,
      "calories": 0
    },
    "2026-01-27": {
      "steps": 0,
      "distance": 0,
      "calories": 0
    },
    "2026-01-28": {
      "steps": 0,
      "distance": 0,
      "calories": 0
    },
    "2026-01-29": {
      "steps": 0,
      "distance": 0,
      "calories": 0
    },
    "2026-01-30": {
      "steps": 0,
      "distance": 0,
      "calories": 0
    },
    "2026-01-31": {
      "steps": 0,
      "distance": 0,
      "calories": 0
    },
    "2026-02-01": {
      "steps": 0,
      "distance": 0,
      "calories": 0
    },
    "2026-02-02": {
      "steps": 0,
      "distance": 0,
      "calories": 0
    },
    "2026-02-03": {
      "steps": 0,
      "distance": 0,
      "calories": 0
    },
    "2026-02-04": {
      "steps": 0,
      "distance": 0,
      "calories": 0
    },
    "2026-02-05": {
      "steps": 0,
      "distance": 0,
      "calories": 0
    },
    "2026-02-06": {
      "steps": 0,
      "distance": 0,
      "calories": 0
    },
    "2026-02-07": {
      "steps": 0,
      "distance": 0,
      "calories": 0
    },
    "2026-02-08": {
      "steps": 0,
      "distance": 0,
      "calories": 0
    },
    "2026-02-09": {
      "steps": 0,
      "distance": 0,
      "calories": 0
    },
    "2026-02-10": {
      "steps": 0,
      "distance": 0,
      "calories": 0
    },
    "2026-02-11": {
      "steps": 0,
      "distance": 0,
      "calories": 0
    },
    "2026-02-12": {
      "steps": 0,
      "distance": 0,
      "calories": 0
    },
    "2026-02-13": {
      "steps": 0,
      "distance": 0,
      "calories": 0
    },
    "2026-02-14": {
      "steps": 0,
      "distance": 0,
      "calories": 0
    },
    "2026-02-15": {
      "steps": 0,
      "distance": 0,
      "calories": 0
    },
    "2026-02-16": {
      "steps": 0,
      "distance": 0,
      "calories": 0
    },
    "2026-02-17": {
      "steps": 0,
      "distance": 0,
      "calories": 0
    },
    "2026-02-18": {
      "steps": 0,
      "distance": 0,
      "calories": 589.3283625281089
    },
    "2026-02-19": {
      "steps": 0,
      "distance": 0,
      "calories": 1812.749940276146
    },
    "2026-02-20": {
      "steps": 102,
      "distance": 70,
      "calories": 1812.749940276146
    }
  },
  "sleep": {},
  "heartRate": {
    "2026-02-20": {
      "min": 60.52613636363636,
      "max": 60.52613636363636,
      "avg": 61,
      "resting": 6
    }
  },
  "moveMinutes": {
    "2026-01-22": {
      "activeMinutes": 0,
      "heartMinutes": 0
    },
    "2026-01-23": {
      "activeMinutes": 0,
      "heartMinutes": 0
    },
    "2026-01-24": {
      "activeMinutes": 0,
      "heartMinutes": 0
    },
    "2026-01-25": {
      "activeMinutes": 0,
      "heartMinutes": 0
    },
    "2026-01-26": {
      "activeMinutes": 0,
      "heartMinutes": 0
    },
    "2026-01-27": {
      "activeMinutes": 0,
      "heartMinutes": 0
    },
    "2026-01-28": {
      "activeMinutes": 0,
      "heartMinutes": 0
    },
    "2026-01-29": {
      "activeMinutes": 0,
      "heartMinutes": 0
    },
    "2026-01-30": {
      "activeMinutes": 0,
      "heartMinutes": 0
    },
    "2026-01-31": {
      "activeMinutes": 0,
      "heartMinutes": 0
    },
    "2026-02-01": {
      "activeMinutes": 0,
      "heartMinutes": 0
    },
    "2026-02-02": {
      "activeMinutes": 0,
      "heartMinutes": 0
    },
    "2026-02-03": {
      "activeMinutes": 0,
      "heartMinutes": 0
    },
    "2026-02-04": {
      "activeMinutes": 0,
      "heartMinutes": 0
    },
    "2026-02-05": {
      "activeMinutes": 0,
      "heartMinutes": 0
    },
    "2026-02-06": {
      "activeMinutes": 0,
      "heartMinutes": 0
    },
    "2026-02-07": {
      "activeMinutes": 0,
      "heartMinutes": 0
    },
    "2026-02-08": {
      "activeMinutes": 0,
      "heartMinutes": 0
    },
    "2026-02-09": {
      "activeMinutes": 0,
      "heartMinutes": 0
    },
    "2026-02-10": {
      "activeMinutes": 0,
      "heartMinutes": 0
    },
    "2026-02-11": {
      "activeMinutes": 0,
      "heartMinutes": 0
    },
    "2026-02-12": {
      "activeMinutes": 0,
      "heartMinutes": 0
    },
    "2026-02-13": {
      "activeMinutes": 0,
      "heartMinutes": 0
    },
    "2026-02-14": {
      "activeMinutes": 0,
      "heartMinutes": 0
    },
    "2026-02-15": {
      "activeMinutes": 0,
      "heartMinutes": 0
    },
    "2026-02-16": {
      "activeMinutes": 0,
      "heartMinutes": 0
    },
    "2026-02-17": {
      "activeMinutes": 0,
      "heartMinutes": 0
    },
    "2026-02-18": {
      "activeMinutes": 0,
      "heartMinutes": 0
    },
    "2026-02-19": {
      "activeMinutes": 0,
      "heartMinutes": 0
    },
    "2026-02-20": {
      "activeMinutes": 0,
      "heartMinutes": 0
    }
  },
  "heartRateZones": {
    "2026-01-22": {
      "zone1Minutes": 0,
      "zone2Minutes": 0,
      "zone3Minutes": 0,
      "zone4Minutes": 0,
      "zone5Minutes": 0,
      "totalActiveMinutes": 0
    },
    "2026-01-23": {
      "zone1Minutes": 0,
      "zone2Minutes": 0,
      "zone3Minutes": 0,
      "zone4Minutes": 0,
      "zone5Minutes": 0,
      "totalActiveMinutes": 0
    },
    "2026-01-24": {
      "zone1Minutes": 0,
      "zone2Minutes": 0,
      "zone3Minutes": 0,
      "zone4Minutes": 0,
      "zone5Minutes": 0,
      "totalActiveMinutes": 0
    },
    "2026-01-25": {
      "zone1Minutes": 0,
      "zone2Minutes": 0,
      "zone3Minutes": 0,
      "zone4Minutes": 0,
      "zone5Minutes": 0,
      "totalActiveMinutes": 0
    },
    "2026-01-26": {
      "zone1Minutes": 0,
      "zone2Minutes": 0,
      "zone3Minutes": 0,
      "zone4Minutes": 0,
      "zone5Minutes": 0,
      "totalActiveMinutes": 0
    },
    "2026-01-27": {
      "zone1Minutes": 0,
      "zone2Minutes": 0,
      "zone3Minutes": 0,
      "zone4Minutes": 0,
      "zone5Minutes": 0,
      "totalActiveMinutes": 0
    },
    "2026-01-28": {
      "zone1Minutes": 0,
      "zone2Minutes": 0,
      "zone3Minutes": 0,
      "zone4Minutes": 0,
      "zone5Minutes": 0,
      "totalActiveMinutes": 0
    },
    "2026-01-29": {
      "zone1Minutes": 0,
      "zone2Minutes": 0,
      "zone3Minutes": 0,
      "zone4Minutes": 0,
      "zone5Minutes": 0,
      "totalActiveMinutes": 0
    },
    "2026-01-30": {
      "zone1Minutes": 0,
      "zone2Minutes": 0,
      "zone3Minutes": 0,
      "zone4Minutes": 0,
      "zone5Minutes": 0,
      "totalActiveMinutes": 0
    },
    "2026-01-31": {
      "zone1Minutes": 0,
      "zone2Minutes": 0,
      "zone3Minutes": 0,
      "zone4Minutes": 0,
      "zone5Minutes": 0,
      "totalActiveMinutes": 0
    },
    "2026-02-01": {
      "zone1Minutes": 0,
      "zone2Minutes": 0,
      "zone3Minutes": 0,
      "zone4Minutes": 0,
      "zone5Minutes": 0,
      "totalActiveMinutes": 0
    },
    "2026-02-02": {
      "zone1Minutes": 0,
      "zone2Minutes": 0,
      "zone3Minutes": 0,
      "zone4Minutes": 0,
      "zone5Minutes": 0,
      "totalActiveMinutes": 0
    },
    "2026-02-03": {
      "zone1Minutes": 0,
      "zone2Minutes": 0,
      "zone3Minutes": 0,
      "zone4Minutes": 0,
      "zone5Minutes": 0,
      "totalActiveMinutes": 0
    },
    "2026-02-04": {
      "zone1Minutes": 0,
      "zone2Minutes": 0,
      "zone3Minutes": 0,
      "zone4Minutes": 0,
      "zone5Minutes": 0,
      "totalActiveMinutes": 0
    },
    "2026-02-05": {
      "zone1Minutes": 0,
      "zone2Minutes": 0,
      "zone3Minutes": 0,
      "zone4Minutes": 0,
      "zone5Minutes": 0,
      "totalActiveMinutes": 0
    },
    "2026-02-06": {
      "zone1Minutes": 0,
      "zone2Minutes": 0,
      "zone3Minutes": 0,
      "zone4Minutes": 0,
      "zone5Minutes": 0,
      "totalActiveMinutes": 0
    },
    "2026-02-07": {
      "zone1Minutes": 0,
      "zone2Minutes": 0,
      "zone3Minutes": 0,
      "zone4Minutes": 0,
      "zone5Minutes": 0,
      "totalActiveMinutes": 0
    },
    "2026-02-08": {
      "zone1Minutes": 0,
      "zone2Minutes": 0,
      "zone3Minutes": 0,
      "zone4Minutes": 0,
      "zone5Minutes": 0,
      "totalActiveMinutes": 0
    },
    "2026-02-09": {
      "zone1Minutes": 0,
      "zone2Minutes": 0,
      "zone3Minutes": 0,
      "zone4Minutes": 0,
      "zone5Minutes": 0,
      "totalActiveMinutes": 0
    },
    "2026-02-10": {
      "zone1Minutes": 0,
      "zone2Minutes": 0,
      "zone3Minutes": 0,
      "zone4Minutes": 0,
      "zone5Minutes": 0,
      "totalActiveMinutes": 0
    },
    "2026-02-11": {
      "zone1Minutes": 0,
      "zone2Minutes": 0,
      "zone3Minutes": 0,
      "zone4Minutes": 0,
      "zone5Minutes": 0,
      "totalActiveMinutes": 0
    },
    "2026-02-12": {
      "zone1Minutes": 0,
      "zone2Minutes": 0,
      "zone3Minutes": 0,
      "zone4Minutes": 0,
      "zone5Minutes": 0,
      "totalActiveMinutes": 0
    },
    "2026-02-13": {
      "zone1Minutes": 0,
      "zone2Minutes": 0,
      "zone3Minutes": 0,
      "zone4Minutes": 0,
      "zone5Minutes": 0,
      "totalActiveMinutes": 0
    },
    "2026-02-14": {
      "zone1Minutes": 0,
      "zone2Minutes": 0,
      "zone3Minutes": 0,
      "zone4Minutes": 0,
      "zone5Minutes": 0,
      "totalActiveMinutes": 0
    },
    "2026-02-15": {
      "zone1Minutes": 0,
      "zone2Minutes": 0,
      "zone3Minutes": 0,
      "zone4Minutes": 0,
      "zone5Minutes": 0,
      "totalActiveMinutes": 0
    },
    "2026-02-16": {
      "zone1Minutes": 0,
      "zone2Minutes": 0,
      "zone3Minutes": 0,
      "zone4Minutes": 0,
      "zone5Minutes": 0,
      "totalActiveMinutes": 0
    },
    "2026-02-17": {
      "zone1Minutes": 0,
      "zone2Minutes": 0,
      "zone3Minutes": 0,
      "zone4Minutes": 0,
      "zone5Minutes": 0,
      "totalActiveMinutes": 0
    },
    "2026-02-18": {
      "zone1Minutes": 0,
      "zone2Minutes": 0,
      "zone3Minutes": 0,
      "zone4Minutes": 0,
      "zone5Minutes": 0,
      "totalActiveMinutes": 0
    },
    "2026-02-19": {
      "zone1Minutes": 0,
      "zone2Minutes": 0,
      "zone3Minutes": 0,
      "zone4Minutes": 0,
      "zone5Minutes": 0,
      "totalActiveMinutes": 0
    },
    "2026-02-20": {
      "zone1Minutes": 0,
      "zone2Minutes": 0,
      "zone3Minutes": 0,
      "zone4Minutes": 0,
      "zone5Minutes": 0,
      "totalActiveMinutes": 0
    },
    "2026-02-21": {
      "zone1Minutes": 0,
      "zone2Minutes": 0,
      "zone3Minutes": 0,
      "zone4Minutes": 0,
      "zone5Minutes": 0,
      "totalActiveMinutes": 0
    }
  },
  "lastUpdated": "2026-02-21T12:49:11.039Z",
  "source": "Google Fit",
  "dataRange": {
    "stepsDays": 90,
    "sleepDays": 0,
    "heartRateDays": 1,
    "moveMinutesDays": 30,
    "heartRateZonesDays": 31
  }
}